[
  {
    "ContainingType": "Peluquer\u00EDaWebApi.Controllers.TServicioController",
    "Method": "Delete",
    "RelativePath": "{id}",
    "HttpMethod": "DELETE",
    "IsController": true,
    "Order": 0,
    "Parameters": [
      {
        "Name": "id",
        "Type": "System.Int32",
        "IsRequired": true
      }
    ],
    "ReturnTypes": []
  },
  {
    "ContainingType": "Peluquer\u00EDaWebApi.Controllers.TServicioController",
    "Method": "Get",
    "RelativePath": "api/TServicio",
    "HttpMethod": "GET",
    "IsController": true,
    "Order": 0,
    "Parameters": [],
    "ReturnTypes": []
  },
  {
    "ContainingType": "Peluquer\u00EDaWebApi.Controllers.TServicioController",
    "Method": "Post",
    "RelativePath": "api/TServicio",
    "HttpMethod": "POST",
    "IsController": true,
    "Order": 0,
    "Parameters": [
      {
        "Name": "servicio",
        "Type": "PeluqueriaBack.Data.Models.TServicio",
        "IsRequired": true
      }
    ],
    "ReturnTypes": []
  },
  {
    "ContainingType": "Peluquer\u00EDaWebApi.Controllers.TServicioController",
    "Method": "Put",
    "RelativePath": "api/TServicio",
    "HttpMethod": "PUT",
    "IsController": true,
    "Order": 0,
    "Parameters": [
      {
        "Name": "servicio",
        "Type": "PeluqueriaBack.Data.Models.TServicio",
        "IsRequired": true
      }
    ],
    "ReturnTypes": []
  },
  {
    "ContainingType": "Peluquer\u00EDaWebApi.Controllers.TServicioController",
    "Method": "GetByCosto",
    "RelativePath": "api/TServicio/GetByCosto",
    "HttpMethod": "GET",
    "IsController": true,
    "Order": 0,
    "Parameters": [
      {
        "Name": "costoMenor",
        "Type": "System.Int32",
        "IsRequired": false
      }
    ],
    "ReturnTypes": []
  },
  {
    "ContainingType": "Peluquer\u00EDaWebApi.Controllers.TServicioController",
    "Method": "Get",
    "RelativePath": "api/TServicio/GetById/{id}",
    "HttpMethod": "GET",
    "IsController": true,
    "Order": 0,
    "Parameters": [
      {
        "Name": "id",
        "Type": "System.Int32",
        "IsRequired": true
      }
    ],
    "ReturnTypes": []
  },
  {
    "ContainingType": "Peluquer\u00EDaWebApi.Controllers.TServicioController",
    "Method": "GetByProm",
    "RelativePath": "api/TServicio/GetByProm",
    "HttpMethod": "GET",
    "IsController": true,
    "Order": 0,
    "Parameters": [
      {
        "Name": "prom",
        "Type": "System.String",
        "IsRequired": false
      }
    ],
    "ReturnTypes": []
  },
  {
    "ContainingType": "Peluquer\u00EDaWebApi.Controllers.TTurnoController",
    "Method": "Get",
    "RelativePath": "api/TTurno",
    "HttpMethod": "GET",
    "IsController": true,
    "Order": 0,
    "Parameters": [],
    "ReturnTypes": []
  },
  {
    "ContainingType": "Peluquer\u00EDaWebApi.Controllers.TTurnoController",
    "Method": "Put",
    "RelativePath": "api/TTurno",
    "HttpMethod": "PUT",
    "IsController": true,
    "Order": 0,
    "Parameters": [
      {
        "Name": "turno",
        "Type": "PeluqueriaBack.Data.Models.TTurno",
        "IsRequired": true
      }
    ],
    "ReturnTypes": []
  },
  {
    "ContainingType": "Peluquer\u00EDaWebApi.Controllers.TTurnoController",
    "Method": "Delete",
    "RelativePath": "api/TTurno",
    "HttpMethod": "DELETE",
    "IsController": true,
    "Order": 0,
    "Parameters": [
      {
        "Name": "id",
        "Type": "System.Int32",
        "IsRequired": false
      },
      {
        "Name": "fechaC",
        "Type": "System.DateTime",
        "IsRequired": false
      },
      {
        "Name": "motivo",
        "Type": "System.String",
        "IsRequired": false
      }
    ],
    "ReturnTypes": []
  },
  {
    "ContainingType": "Peluquer\u00EDaWebApi.Controllers.TTurnoController",
    "Method": "PostAsync",
    "RelativePath": "api/TTurno",
    "HttpMethod": "POST",
    "IsController": true,
    "Order": 0,
    "Parameters": [
      {
        "Name": "turno",
        "Type": "PeluqueriaBack.Data.Models.TTurno",
        "IsRequired": true
      }
    ],
    "ReturnTypes": []
  },
  {
    "ContainingType": "Peluquer\u00EDaWebApi.Controllers.TTurnoController",
    "Method": "GetByCliente",
    "RelativePath": "api/TTurno/GetByCliente",
    "HttpMethod": "GET",
    "IsController": true,
    "Order": 0,
    "Parameters": [
      {
        "Name": "cliente",
        "Type": "System.String",
        "IsRequired": false
      }
    ],
    "ReturnTypes": []
  },
  {
    "ContainingType": "Peluquer\u00EDaWebApi.Controllers.TTurnoController",
    "Method": "GetByFechas",
    "RelativePath": "api/TTurno/GetByFecha",
    "HttpMethod": "GET",
    "IsController": true,
    "Order": 0,
    "Parameters": [
      {
        "Name": "fecha1",
        "Type": "System.String",
        "IsRequired": false
      }
    ],
    "ReturnTypes": []
  },
  {
    "ContainingType": "Peluquer\u00EDaWebApi.Controllers.TTurnoController",
    "Method": "GetById",
    "RelativePath": "api/TTurno/GetById",
    "HttpMethod": "GET",
    "IsController": true,
    "Order": 0,
    "Parameters": [
      {
        "Name": "id",
        "Type": "System.Int32",
        "IsRequired": false
      }
    ],
    "ReturnTypes": []
  }
]